{
  "editor:add-cursor-above": [
    {
      "modifiers": [
        "Alt",
        "Shift"
      ],
      "key": "ArrowUp"
    }
  ],
  "editor:add-cursor-below": [
    {
      "modifiers": [
        "Alt",
        "Shift"
      ],
      "key": "ArrowDown"
    }
  ],
  "file-explorer:new-file-in-new-pane": [],
  "file-explorer:new-folder": [
    {
      "modifiers": [
        "Mod",
        "Shift"
      ],
      "key": "N"
    }
  ],
  "editor:toggle-numbered-list": [
    {
      "modifiers": [
        "Mod",
        "Shift"
      ],
      "key": "3"
    }
  ],
  "editor:toggle-bullet-list": [
    {
      "modifiers": [
        "Mod",
        "Shift"
      ],
      "key": "2"
    }
  ],
  "command-palette:open": [
    {
      "modifiers": [
        "Mod"
      ],
      "key": "P"
    },
    {
      "modifiers": [],
      "key": "F1"
    }
  ],
  "app:open-settings": [
    {
      "modifiers": [
        "Mod"
      ],
      "key": ","
    }
  ],
  "app:open-help": [
    {
      "modifiers": [
        "Alt"
      ],
      "key": "H"
    }
  ],
  "editor:fold-less": [
    {
      "modifiers": [
        "Alt"
      ],
      "key": "]"
    },
    {
      "modifiers": [
        "Alt"
      ],
      "key": "ArrowDown"
    }
  ],
  "editor:fold-more": [
    {
      "modifiers": [
        "Alt"
      ],
      "key": "["
    },
    {
      "modifiers": [
        "Alt"
      ],
      "key": "ArrowUp"
    }
  ]
}
